LICENSE
README.md
pyproject.toml
setup.py
src/torchwrench/__init__.py
src/torchwrench/__main__.py
src/torchwrench/entries.py
src/torchwrench.egg-info/PKG-INFO
src/torchwrench.egg-info/SOURCES.txt
src/torchwrench.egg-info/dependency_links.txt
src/torchwrench.egg-info/entry_points.txt
src/torchwrench.egg-info/requires.txt
src/torchwrench.egg-info/top_level.txt
src/torchwrench/core/__init__.py
src/torchwrench/core/config.py
src/torchwrench/core/dtype_enum.py
src/torchwrench/core/make.py
src/torchwrench/core/packaging.py
src/torchwrench/core/version.py
src/torchwrench/extras/__init__.py
src/torchwrench/extras/colorlog.py
src/torchwrench/extras/safetensors.py
src/torchwrench/extras/tensorboard.py
src/torchwrench/extras/torchaudio.py
src/torchwrench/extras/hdf/__init__.py
src/torchwrench/extras/hdf/common.py
src/torchwrench/extras/hdf/dataset.py
src/torchwrench/extras/hdf/pack.py
src/torchwrench/extras/numpy/__init__.py
src/torchwrench/extras/numpy/_numpy_fallback.py
src/torchwrench/extras/numpy/definitions.py
src/torchwrench/extras/numpy/functional.py
src/torchwrench/extras/numpy/saving.py
src/torchwrench/extras/numpy/scan_info.py
src/torchwrench/extras/pandas/__init__.py
src/torchwrench/extras/pandas/_pandas_fallback.py
src/torchwrench/extras/speechbrain/__init__.py
src/torchwrench/extras/speechbrain/_speechbrain_fallback.py
src/torchwrench/extras/yaml/__init__.py
src/torchwrench/extras/yaml/_yaml_fallback.py
src/torchwrench/extras/yaml/yaml.py
src/torchwrench/hub/__init__.py
src/torchwrench/hub/download.py
src/torchwrench/hub/paths.py
src/torchwrench/hub/registry.py
src/torchwrench/nn/__init__.py
src/torchwrench/nn/functional/__init__.py
src/torchwrench/nn/functional/activation.py
src/torchwrench/nn/functional/checksum.py
src/torchwrench/nn/functional/cropping.py
src/torchwrench/nn/functional/indices.py
src/torchwrench/nn/functional/make.py
src/torchwrench/nn/functional/mask.py
src/torchwrench/nn/functional/multiclass.py
src/torchwrench/nn/functional/multilabel.py
src/torchwrench/nn/functional/new.py
src/torchwrench/nn/functional/others.py
src/torchwrench/nn/functional/padding.py
src/torchwrench/nn/functional/powerset.py
src/torchwrench/nn/functional/predicate.py
