Metadata-Version: 2.4
Name: torchwrench
Version: 0.7.5
Summary: Collection of functions and modules to help development in PyTorch.
Author-email: "Étienne Labbé (Labbeti)" <labbeti.pub@gmail.com>
Maintainer-email: "Étienne Labbé (Labbeti)" <labbeti.pub@gmail.com>
License: MIT License
Project-URL: Homepage, https://pypi.org/project/torchwrench/
Project-URL: Documentation, https://torchwrench.readthedocs.io/
Project-URL: Repository, https://github.com/Labbeti/torchwrench.git
Project-URL: Changelog, https://github.com/Labbeti/torchwrench/blob/main/CHANGELOG.md
Project-URL: Tracker, https://github.com/Labbeti/torchwrench/issues
Keywords: pytorch,deep-learning
Classifier: Intended Audience :: Developers
Classifier: Intended Audience :: Science/Research
Classifier: Programming Language :: Python :: 3
Classifier: Programming Language :: Python :: 3.8
Classifier: Programming Language :: Python :: 3.9
Classifier: Programming Language :: Python :: 3.10
Classifier: Programming Language :: Python :: 3.11
Classifier: Programming Language :: Python :: 3.12
Classifier: Programming Language :: Python :: 3.13
Classifier: Topic :: Scientific/Engineering
Classifier: Topic :: Scientific/Engineering :: Artificial Intelligence
Classifier: Operating System :: OS Independent
Requires-Python: >=3.8
License-File: LICENSE
Requires-Dist: pythonwrench<0.5.0,>=0.3.0
Requires-Dist: torch>=1.10.0
Requires-Dist: typing-extensions>=4.10.0
Provides-Extra: dev
Requires-Dist: coverage[toml]; extra == "dev"
Requires-Dist: ipython; extra == "dev"
Requires-Dist: pre-commit; extra == "dev"
Requires-Dist: pytest; extra == "dev"
Requires-Dist: ruff>=0.12.0; extra == "dev"
Requires-Dist: setuptools; extra == "dev"
Requires-Dist: soundfile; extra == "dev"
Requires-Dist: sphinx; extra == "dev"
Requires-Dist: sphinx-press-theme; extra == "dev"
Requires-Dist: twine; extra == "dev"
Requires-Dist: typing-extensions>=4.10.0; extra == "dev"
Requires-Dist: ipykernel; extra == "dev"
Requires-Dist: numpy!=2.0.0,!=2.0.1,!=2.0.2; extra == "dev"
Provides-Extra: extras
Requires-Dist: colorlog; extra == "extras"
Requires-Dist: h5py; extra == "extras"
Requires-Dist: numpy!=2.0.0,!=2.0.1,!=2.0.2; extra == "extras"
Requires-Dist: omegaconf; extra == "extras"
Requires-Dist: pandas; extra == "extras"
Requires-Dist: pyyaml; extra == "extras"
Requires-Dist: safetensors; extra == "extras"
Requires-Dist: scipy; extra == "extras"
Requires-Dist: speechbrain>=1.0.3; extra == "extras"
Requires-Dist: tensorboard; extra == "extras"
Requires-Dist: torchaudio; extra == "extras"
Requires-Dist: torchvision; extra == "extras"
Requires-Dist: tqdm; extra == "extras"
Dynamic: license-file
